login_gui/__init__.py
login_gui/frame.py
login_gui/loader.py
login_gui/user.py
login_gui/version.py
tests/__init__.py
tests/runner.py
tests/test_gui.py
tests/test_user.py
login_gui-2.0.0.dist-info/LICENSE
login_gui-2.0.0.dist-info/METADATA
login_gui-2.0.0.dist-info/WHEEL
login_gui-2.0.0.dist-info/top_level.txt
login_gui-2.0.0.dist-info/RECORD
