Metadata-Version: 2.1
Name: login-gui
Version: 2.0.0
Summary: Gui with User/Password requesting and save in base64
Home-page: https://github.com/sashasoft90/login-gui
Author: Alexander Sacharov
Author-email: alexander.sacharov@t-online.de
License: MIT
Platform: UNKNOWN
Classifier: Development Status :: 5 - Production/Stable
Classifier: Intended Audience :: Developers
Classifier: License :: OSI Approved :: MIT License
Classifier: Programming Language :: Python
Classifier: Programming Language :: Python :: 3
Classifier: Programming Language :: Python :: 3.8
Classifier: Topic :: Software Development :: Libraries :: Python Modules
Classifier: Topic :: Utilities
License-File: LICENSE
Requires-Dist: py-singleton
